journalism_workflow
orchestra
simple_workflow
