Metadata-Version: 2.1
Name: orchestra
Version: 1.0.59
Summary: A framework for building complex expert workflows.
Home-page: https://github.com/b12io/orchestra
Author: B12 (Unlimited Labs, Inc.)
Author-email: hello@b12.io
License: Apache 2
Download-URL: https://github.com/b12io/orchestra/tarball/v1.0.59
Keywords: crowdsourcing,workflows
Platform: UNKNOWN
License-File: LICENSE
License-File: NOTICE
